setup.py
budiluhur/__init__.py
budiluhur/jadwal/__init__.py
budiluhur/jadwal/fakultas.py
budiluhur_jadwal.egg-info/PKG-INFO
budiluhur_jadwal.egg-info/SOURCES.txt
budiluhur_jadwal.egg-info/dependency_links.txt
budiluhur_jadwal.egg-info/requires.txt
budiluhur_jadwal.egg-info/top_level.txt