Metadata-Version: 1.1
Name: budiluhur-jadwal
Version: 1.1.0
Summary: Python API Jadwal Perkulahan Budiluhur
Home-page: https://github.com/yanwarsolahudinn/budiluhur-jadwal
Author: Yanwar Solahudin
Author-email: yanwarsolahudinn@gmail.com
License: UNKNOWN
Download-URL: https://github.com/yanwarsolahudinn/budiluhur-jadwal/archive/master.zip
Keywords: API,JSON,budiluhur,jadwal,track,schedule,kuliah
Platform: UNKNOWN
Classifier: Development Status :: 5 - Production/Stable
Classifier: Intended Audience :: Developers
Classifier: Natural Language :: Indonesian
Classifier: License :: OSI Approved :: MIT License
Classifier: Operating System :: OS Independent
Classifier: Programming Language :: Python
Classifier: Programming Language :: Python :: 3
Classifier: Programming Language :: Python :: 3.3
Classifier: Programming Language :: Python :: 3.4
Classifier: Programming Language :: Python :: 3.5
Classifier: Topic :: Software Development :: Libraries :: Python Modules
